{
	"animations": [
		{
			"offsets": [
				-15,
				36
			],
			"loop": false,
			"fps": 24,
			"anim": "idle",
			"indices": [],
			"name": "matt idle"
		},
		{
			"offsets": [
				19,
				1
			],
			"loop": false,
			"fps": 24,
			"anim": "singLEFT",
			"indices": [],
			"name": "matt left"
		},
		{
			"offsets": [
				-27,
				56
			],
			"loop": false,
			"fps": 24,
			"anim": "singUP",
			"indices": [],
			"name": "matt up"
		},
		{
			"offsets": [
				3,
				3
			],
			"loop": false,
			"fps": 24,
			"anim": "singRIGHT",
			"indices": [],
			"name": "matt right"
		},
		{
			"offsets": [
				-27,
				11
			],
			"loop": false,
			"fps": 24,
			"anim": "singDOWN",
			"indices": [],
			"name": "matt down"
		}
	],
	"no_antialiasing": true,
	"image": "characters/gmatt",
	"position": [
		60,
		310
	],
	"healthicon": "gmatt",
	"flip_x": false,
	"healthbar_colors": [
		0,
		255,
		0
	],
	"camera_position": [
		0,
		0
	],
	"sing_duration": 4,
	"scale": 1
}