{
	"animations": [
		{
			"loop": true,
			"offsets": [
				0,
				0
			],
			"anim": "idle",
			"fps": 24,
			"name": "Symbol 24",
			"indices": []
		},
		{
			"loop": true,
			"offsets": [
				0,
				0
			],
			"anim": "singUP",
			"fps": 24,
			"name": "Symbol 24",
			"indices": []
		}
	],
	"no_antialiasing": false,
	"image": "characters/BF Boxing",
	"position": [
		-300,
		40
	],
	"healthicon": "bf",
	"flip_x": false,
	"healthbar_colors": [
		49,
		176,
		209
	],
	"camera_position": [
		0,
		0
	],
	"sing_duration": 6.1,
	"scale": 2
}